[
  {
    "key": "d97G24dAFNaT5kN4MP26",
    "name": "美容室に行く"
  },
  {
    "key": "d97G24dAFNaT5kN4MP26",
    "name": "カフェでランチ"
  },
  {
    "key": "d97G24dAFNaT5kN4MP26",
    "name": "映画を見る"
  },
  {
    "key": "d97G24dAFNaT5kN4MP26",
    "name": "図書館で読書"
  },
  {
    "key": "d97G24dAFNaT5kN4MP26",
    "name": "カレーライスの材料を買う"
  },
  {
    "key": "d97G24dAFNaT5kN4MP26",
    "name": "晩御飯にカレーを作る"
  },
  {
    "key": "4U8fPEQGKMuSQ6sdbfgQ",
    "name": "ヘッドフォン"
  },
  {
    "key": "4U8fPEQGKMuSQ6sdbfgQ",
    "name": "USB"
  },
  {
    "key": "4U8fPEQGKMuSQ6sdbfgQ",
    "name": "ボールペン"
  },
  {
    "key": "4U8fPEQGKMuSQ6sdbfgQ",
    "name": "シャンプー"
  },
  {
    "key": "4U8fPEQGKMuSQ6sdbfgQ",
    "name": "コップ"
  },
  {
    "key": "pB9z7PoKQB9BWgBkVS4X",
    "name": "京都旅行"
  },
  {
    "key": "pB9z7PoKQB9BWgBkVS4X",
    "name": "車を買う"
  },
  {
    "key": "xRiiUskE7dxbHeSZafRK",
    "name": "賃貸住宅の解約"
  },
  {
    "key": "xRiiUskE7dxbHeSZafRK",
    "name": "郵便物の転送手続き"
  },
  {
    "key": "xRiiUskE7dxbHeSZafRK",
    "name": "転出届の提出"
  }
]
